checklist/__init__.py
checklist/abstract_test.py
checklist/editor.py
checklist/expect.py
checklist/multilingual.py
checklist/perturb.py
checklist/pred_wrapper.py
checklist/test_suite.py
checklist/test_types.py
checklist/text_generation.py
checklist/data/names.json
checklist/data/wikidata.pkl
checklist/data/lexicons/basic.json
checklist/viewer/__init__.py
checklist/viewer/fake_data.py
checklist/viewer/suite_summarizer.py
checklist/viewer/template_editor.py
checklist/viewer/test_summarizer.py
checklist/viewer/viewer.py
checklist/viewer/static/__init__.py
checklist/viewer/static/bundle.js
checklist/viewer/static/bundle.js.map
checklist/viewer/static/custom.js
checklist/viewer/static/extension.js
checklist/viewer/static/index.js
checklist/viewer/static/index.js.map
checklist_pattern-0.0.11.dist-info/LICENSE
checklist_pattern-0.0.11.dist-info/METADATA
checklist_pattern-0.0.11.dist-info/WHEEL
checklist_pattern-0.0.11.dist-info/top_level.txt
checklist_pattern-0.0.11.dist-info/RECORD
